agility_cms/__init__.py
agility_cms/client.py
agility_cms-0.1.0.dist-info/LICENSE
agility_cms-0.1.0.dist-info/METADATA
agility_cms-0.1.0.dist-info/WHEEL
agility_cms-0.1.0.dist-info/top_level.txt
agility_cms-0.1.0.dist-info/RECORD
