Metadata-Version: 2.1
Name: agility-cms
Version: 0.1.0
Summary: Python Fetch SDK for Agility CMS
Home-page: https://github.com/agility/agilitycms-python-sdk
Author: James Rao
Author-email: jamesnarayanrao@gmail.com
License: UNKNOWN
Project-URL: Bug Tracker, https://github.com/agility/agilitycms-python-sdk/issues
Platform: UNKNOWN
Classifier: Programming Language :: Python :: 3
Classifier: License :: OSI Approved :: MIT License
Classifier: Operating System :: OS Independent
Requires-Python: >=3.6
License-File: LICENSE
Requires-Dist: requests
